entifyfishing_client/__init__.py
entifyfishing_client/api/__init__.py
entifyfishing_client/api/knowledge_base/__init__.py
entifyfishing_client/api/knowledge_base/get_concept.py
entifyfishing_client/api/knowledge_base/term_lookup.py
entifyfishing_client/api/query_processing/__init__.py
entifyfishing_client/api/query_processing/disambiguate.py
entifyfishing_client/client.py
entifyfishing_client/models/__init__.py
entifyfishing_client/models/bounding_box.py
entifyfishing_client/models/category.py
entifyfishing_client/models/concept.py
entifyfishing_client/models/definition.py
entifyfishing_client/models/disambiguate_form.py
entifyfishing_client/models/entity.py
entifyfishing_client/models/language.py
entifyfishing_client/models/monolingual_text.py
entifyfishing_client/models/multilingual_term.py
entifyfishing_client/models/page.py
entifyfishing_client/models/quantity.py
entifyfishing_client/models/query_parameters.py
entifyfishing_client/models/query_result_file.py
entifyfishing_client/models/query_result_term_vector.py
entifyfishing_client/models/query_result_text.py
entifyfishing_client/models/sense.py
entifyfishing_client/models/sentence.py
entifyfishing_client/models/statement.py
entifyfishing_client/models/term_senses.py
entifyfishing_client/models/time.py
entifyfishing_client/models/uploaded_file.py
entifyfishing_client/models/weighted_term.py
entifyfishing_client/models/weighted_term_entities.py
entifyfishing_client/py.typed
entifyfishing_client/types.py
entifyfishing_client-0.4.1.dist-info/LICENSE
entifyfishing_client-0.4.1.dist-info/WHEEL
entifyfishing_client-0.4.1.dist-info/METADATA
entifyfishing_client-0.4.1.dist-info/RECORD
